{"trial_id": "08e912e20f0790ec16500439827bd0b9", "hyperparameters": {"space": [{"class_name": "Boolean", "config": {"name": "structured_data_block_1/normalize", "default": false, "conditions": []}}, {"class_name": "Boolean", "config": {"name": "structured_data_block_1/dense_block_1/use_batchnorm", "default": false, "conditions": []}}, {"class_name": "Choice", "config": {"name": "structured_data_block_1/dense_block_1/num_layers", "default": 2, "conditions": [], "values": [1, 2, 3], "ordered": true}}, {"class_name": "Choice", "config": {"name": "structured_data_block_1/dense_block_1/units_0", "default": 32, "conditions": [], "values": [16, 32, 64, 128, 256, 512, 1024], "ordered": true}}, {"class_name": "Choice", "config": {"name": "structured_data_block_1/dense_block_1/dropout", "default": 0.0, "conditions": [], "values": [0.0, 0.25, 0.5], "ordered": true}}, {"class_name": "Choice", "config": {"name": "structured_data_block_1/dense_block_1/units_1", "default": 32, "conditions": [], "values": [16, 32, 64, 128, 256, 512, 1024], "ordered": true}}, {"class_name": "Choice", "config": {"name": "regression_head_1/dropout", "default": 0, "conditions": [], "values": [0.0, 0.25, 0.5], "ordered": true}}, {"class_name": "Choice", "config": {"name": "optimizer", "default": "adam", "conditions": [], "values": ["adam", "sgd", "adam_weight_decay"], "ordered": false}}, {"class_name": "Choice", "config": {"name": "learning_rate", "default": 0.001, "conditions": [], "values": [0.1, 0.01, 0.001, 0.0001, 2e-05, 1e-05], "ordered": true}}], "values": {"structured_data_block_1/normalize": true, "structured_data_block_1/dense_block_1/use_batchnorm": false, "structured_data_block_1/dense_block_1/num_layers": 2, "structured_data_block_1/dense_block_1/units_0": 32, "structured_data_block_1/dense_block_1/dropout": 0, "structured_data_block_1/dense_block_1/units_1": 32, "regression_head_1/dropout": 0.25, "optimizer": "adam", "learning_rate": 0.001}}, "metrics": {"metrics": {"loss": {"direction": "min", "observations": [{"value": [0.17933984100818634], "step": 0}, {"value": [0.1655055433511734], "step": 1}, {"value": [0.11288484930992126], "step": 2}, {"value": [0.06679828464984894], "step": 3}, {"value": [0.05208655074238777], "step": 4}, {"value": [0.03949536755681038], "step": 5}, {"value": [0.03356868773698807], "step": 6}, {"value": [0.022602451965212822], "step": 7}, {"value": [0.01774551533162594], "step": 8}, {"value": [0.014430951327085495], "step": 9}, {"value": [0.01114332303404808], "step": 10}, {"value": [0.007306696847081184], "step": 11}, {"value": [0.004928449634462595], "step": 12}, {"value": [0.005305660888552666], "step": 13}, {"value": [0.0028299549594521523], "step": 14}]}, "mean_squared_error": {"direction": "min", "observations": [{"value": [0.07036352157592773], "step": 0}, {"value": [0.050050146877765656], "step": 1}, {"value": [0.026115842163562775], "step": 2}, {"value": [0.015062179416418076], "step": 3}, {"value": [0.007534390315413475], "step": 4}, {"value": [0.004616189748048782], "step": 5}, {"value": [0.004484944511204958], "step": 6}, {"value": [0.0014154688687995076], "step": 7}, {"value": [0.0008602803573012352], "step": 8}, {"value": [0.0009334410424344242], "step": 9}, {"value": [0.0018579094903543591], "step": 10}, {"value": [0.0008460400276817381], "step": 11}, {"value": [0.0003499806043691933], "step": 12}, {"value": [0.004171756096184254], "step": 13}, {"value": [0.0007801172905601561], "step": 14}]}, "val_loss": {"direction": "min", "observations": [{"value": [5708.54052734375], "step": 0}, {"value": [4017.81884765625], "step": 1}, {"value": [3320.722412109375], "step": 2}, {"value": [1035.832275390625], "step": 3}, {"value": [110.68002319335938], "step": 4}, {"value": [553.828857421875], "step": 5}, {"value": [1040.0596923828125], "step": 6}, {"value": [3959.658447265625], "step": 7}, {"value": [3317.556396484375], "step": 8}, {"value": [4772.52392578125], "step": 9}, {"value": [4147.50146484375], "step": 10}, {"value": [4627.017578125], "step": 11}, {"value": [4492.67919921875], "step": 12}, {"value": [4577.2021484375], "step": 13}, {"value": [4410.94873046875], "step": 14}]}, "val_mean_squared_error": {"direction": "min", "observations": [{"value": [1616230144.0], "step": 0}, {"value": [800561920.0], "step": 1}, {"value": [546869440.0], "step": 2}, {"value": [53205076.0], "step": 3}, {"value": [606531.625], "step": 4}, {"value": [15209504.0], "step": 5}, {"value": [53646752.0], "step": 6}, {"value": [777659456.0], "step": 7}, {"value": [545897664.0], "step": 8}, {"value": [1129726336.0], "step": 9}, {"value": [853199040.0], "step": 10}, {"value": [1061891904.0], "step": 11}, {"value": [1001126592.0], "step": 12}, {"value": [1039152064.0], "step": 13}, {"value": [965034560.0], "step": 14}]}}}, "score": 110.68002319335938, "best_step": 4, "status": "COMPLETED"}